<?xml version="1.0" encoding="utf-8" standalone="yes"?><w:comments xmlns:wpc="http://schemas.microsoft.com/office/word/2010/wordprocessingCanvas" xmlns:cx="http://schemas.microsoft.com/office/drawing/2014/chartex" xmlns:cx1="http://schemas.microsoft.com/office/drawing/2015/9/8/chartex" xmlns:cx2="http://schemas.microsoft.com/office/drawing/2015/10/21/chartex" xmlns:cx3="http://schemas.microsoft.com/office/drawing/2016/5/9/chartex" xmlns:cx4="http://schemas.microsoft.com/office/drawing/2016/5/10/chartex" xmlns:cx5="http://schemas.microsoft.com/office/drawing/2016/5/11/chartex" xmlns:cx6="http://schemas.microsoft.com/office/drawing/2016/5/12/chartex" xmlns:cx7="http://schemas.microsoft.com/office/drawing/2016/5/13/chartex" xmlns:cx8="http://schemas.microsoft.com/office/drawing/2016/5/14/chartex" xmlns:mc="http://schemas.openxmlformats.org/markup-compatibility/2006" xmlns:aink="http://schemas.microsoft.com/office/drawing/2016/ink" xmlns:am3d="http://schemas.microsoft.com/office/drawing/2017/model3d" xmlns:o="urn:schemas-microsoft-com:office:office" xmlns:oel="http://schemas.microsoft.com/office/2019/extlst" xmlns:r="http://schemas.openxmlformats.org/officeDocument/2006/relationships" xmlns:m="http://schemas.openxmlformats.org/officeDocument/2006/math" xmlns:v="urn:schemas-microsoft-com:vml" xmlns:wp14="http://schemas.microsoft.com/office/word/2010/wordprocessingDrawing" xmlns:wp="http://schemas.openxmlformats.org/drawingml/2006/wordprocessingDrawing" xmlns:w10="urn:schemas-microsoft-com:office:word" xmlns:w="http://schemas.openxmlformats.org/wordprocessingml/2006/main" xmlns:w14="http://schemas.microsoft.com/office/word/2010/wordml" xmlns:w15="http://schemas.microsoft.com/office/word/2012/wordml" xmlns:w16cex="http://schemas.microsoft.com/office/word/2018/wordml/cex" xmlns:w16cid="http://schemas.microsoft.com/office/word/2016/wordml/cid" xmlns:w16="http://schemas.microsoft.com/office/word/2018/wordml" xmlns:w16sdtdh="http://schemas.microsoft.com/office/word/2020/wordml/sdtdatahash" xmlns:w16se="http://schemas.microsoft.com/office/word/2015/wordml/symex" xmlns:wpg="http://schemas.microsoft.com/office/word/2010/wordprocessingGroup" xmlns:wpi="http://schemas.microsoft.com/office/word/2010/wordprocessingInk" xmlns:wne="http://schemas.microsoft.com/office/word/2006/wordml" xmlns:wps="http://schemas.microsoft.com/office/word/2010/wordprocessingShape" mc:Ignorable="w14 w15 w16se w16cid w16 w16cex w16sdtdh wp14"><w:comment w:initials="ABdS" w:author="Aline Silva" w:date="2022-08-11T14:46:00Z" w:id="4"><w:p w:rsidR="002E4356" w:rsidP="009F2E37" w:rsidRDefault="002E4356" w14:paraId="09E76CBE" w14:textId="77777777"><w:pPr><w:pStyle w:val="Textodecomentrio" /></w:pPr><w:r><w:rPr><w:rStyle w:val="Refdecomentrio" /></w:rPr><w:annotationRef /></w:r><w:r><w:t>@thiago, tem como criar um ícone que ilustre as atividades?</w:t></w:r></w:p></w:comment><w:comment w:initials="ABdS" w:author="Aline Silva" w:date="2022-08-11T15:12:00Z" w:id="9"><w:p w:rsidR="009711BD" w:rsidP="00C51954" w:rsidRDefault="009711BD" w14:paraId="37FB6D62" w14:textId="77777777"><w:pPr><w:pStyle w:val="Textodecomentrio" /></w:pPr><w:r><w:rPr><w:rStyle w:val="Refdecomentrio" /></w:rPr><w:annotationRef /></w:r><w:r><w:t>Confirmar.</w:t></w:r><w:r><w:rPr><w:rStyle w:val="CommentReference" /></w:rPr><w:annotationRef /></w:r></w:p></w:comment><w:comment w:initials="ABdS" w:author="Aline Silva" w:date="2022-08-11T15:13:00Z" w:id="10"><w:p w:rsidR="008D22FF" w:rsidP="007C683B" w:rsidRDefault="008D22FF" w14:paraId="6D203490" w14:textId="77777777"><w:pPr><w:pStyle w:val="Textodecomentrio" /></w:pPr><w:r><w:rPr><w:rStyle w:val="Refdecomentrio" /></w:rPr><w:annotationRef /></w:r><w:r><w:t>Confirmar.</w:t></w:r><w:r><w:rPr><w:rStyle w:val="CommentReference" /></w:rPr><w:annotationRef /></w:r></w:p></w:comment><w:comment w:initials="BO" w:author="Breno Tiago Novello Trotta de Oliveira" w:date="2022-04-27T11:13:00Z" w:id="11"><w:p w:rsidR="00376655" w:rsidP="00376655" w:rsidRDefault="00376655" w14:paraId="4D302FFD" w14:textId="00697FA4"><w:r><w:t>Poderia colocar "Ciencia de Dados". Eu entendi o contexto, até acho que "aprendizado de maquina" faz mais sentido, mas usaria para enfatizar o nome do curso.</w:t></w:r><w:r><w:annotationRef /></w:r></w:p></w:comment><w:comment w:initials="ECG" w:author="Eduardo Correa Goncalves" w:date="2022-04-28T13:53:00Z" w:id="12"><w:p w:rsidR="00376655" w:rsidP="00376655" w:rsidRDefault="00376655" w14:paraId="4CADD5B3" w14:textId="77777777"><w:pPr><w:pStyle w:val="Textodecomentrio" /></w:pPr><w:r><w:rPr><w:rStyle w:val="Refdecomentrio" /></w:rPr><w:annotationRef /></w:r><w:r><w:t>Ok!</w:t></w:r></w:p></w:comment><w:comment w:initials="ECG" w:author="Eduardo Correa Goncalves" w:date="2022-04-28T14:00:00Z" w:id="13"><w:p w:rsidR="00376655" w:rsidP="00376655" w:rsidRDefault="00376655" w14:paraId="43EC173C" w14:textId="77777777"><w:pPr><w:pStyle w:val="Textodecomentrio" /></w:pPr><w:r><w:rPr><w:rStyle w:val="Refdecomentrio" /></w:rPr><w:annotationRef /></w:r></w:p></w:comment><w:comment w:initials="BO" w:author="Breno Tiago Novello Trotta de Oliveira" w:date="2022-04-27T11:34:00Z" w:id="14"><w:p w:rsidR="00D17359" w:rsidP="00D17359" w:rsidRDefault="00D17359" w14:paraId="182BE069" w14:textId="11641327"><w:r><w:t>Essa sigla de BASE DE DADOS  foi definida anteriormente no modulo 2?</w:t></w:r><w:r><w:annotationRef /></w:r></w:p></w:comment><w:comment w:initials="ECG" w:author="Eduardo Correa Goncalves" w:date="2022-04-28T14:12:00Z" w:id="15"><w:p w:rsidR="00D17359" w:rsidP="00D17359" w:rsidRDefault="00D17359" w14:paraId="664CCA73" w14:textId="77777777"><w:pPr><w:pStyle w:val="Textodecomentrio" /></w:pPr><w:r><w:rPr><w:rStyle w:val="Refdecomentrio" /></w:rPr><w:annotationRef /></w:r><w:r><w:t>Acho que não, troquei então no texto</w:t></w:r></w:p></w:comment><w:comment w:initials="MM" w:author="Marcelo Rodrigues de Holanda Maia" w:date="2022-08-23T16:56:35" w:id="763458662"><w:p w:rsidR="58EC5498" w:rsidRDefault="58EC5498" w14:paraId="22BED592" w14:textId="21C50234"><w:pPr><w:pStyle w:val="CommentText" /></w:pPr><w:r w:rsidR="58EC5498"><w:rPr /><w:t>Esta questão foi revisada no Módulo I.</w:t></w:r><w:r><w:rPr><w:rStyle w:val="CommentReference" /></w:rPr><w:annotationRef /></w:r><w:r><w:rPr><w:rStyle w:val="CommentReference" /></w:rPr><w:annotationRef /></w:r></w:p><w:p w:rsidR="58EC5498" w:rsidRDefault="58EC5498" w14:paraId="08722176" w14:textId="3E03915F"><w:pPr><w:pStyle w:val="CommentText" /></w:pPr><w:r w:rsidR="58EC5498"><w:rPr /><w:t>Não é o problema que é supervisionado, mas sim o aprendizado aplicado ao problema.</w:t></w:r></w:p><w:p w:rsidR="58EC5498" w:rsidRDefault="58EC5498" w14:paraId="1009B77B" w14:textId="3544EA55"><w:pPr><w:pStyle w:val="CommentText" /></w:pPr><w:r w:rsidR="58EC5498"><w:rPr /><w:t>Sugestão de ajuste inserida no texto.</w:t></w:r></w:p></w:comment><w:comment w:initials="MM" w:author="Marcelo Rodrigues de Holanda Maia" w:date="2022-08-23T17:11:33" w:id="935760355"><w:p w:rsidR="58EC5498" w:rsidRDefault="58EC5498" w14:paraId="0C92C1E1" w14:textId="08468FA0"><w:pPr><w:pStyle w:val="CommentText" /></w:pPr><w:r w:rsidR="58EC5498"><w:rPr /><w:t>Sugeri a introdução do "em geral" porque essa afirmação não é válida no caso de classificação multi-rótulo.</w:t></w:r><w:r><w:rPr><w:rStyle w:val="CommentReference" /></w:rPr><w:annotationRef /></w:r><w:r><w:rPr><w:rStyle w:val="CommentReference" /></w:rPr><w:annotationRef /></w:r></w:p></w:comment><w:comment w:initials="MM" w:author="Marcelo Rodrigues de Holanda Maia" w:date="2022-09-09T10:32:23" w:id="1733579351"><w:p w:rsidR="4A7A2789" w:rsidRDefault="4A7A2789" w14:paraId="1ECEC55B" w14:textId="58F9C426"><w:pPr><w:pStyle w:val="CommentText" /></w:pPr><w:r w:rsidR="4A7A2789"><w:rPr /><w:t>Nota para o designer: seria interessante usar recursos visuais para essa explicação. Podemos discutir possibilidades quando for implementar.</w:t></w:r><w:r><w:rPr><w:rStyle w:val="CommentReference" /></w:rPr><w:annotationRef /></w:r></w:p></w:comment><w:comment w:initials="MM" w:author="Marcelo Rodrigues de Holanda Maia" w:date="2022-09-09T10:47:34" w:id="179282308"><w:p w:rsidR="4A7A2789" w:rsidP="05D12FCE" w:rsidRDefault="4A7A2789" w14:paraId="751C900B" w14:textId="1A489A94"><w:pPr><w:pStyle w:val="CommentText" /></w:pPr><w:r w:rsidR="05D12FCE"><w:rPr /><w:t>A definição de partição "pura" apresentada anteriormente foi "partição em que há predominância de um rótulo de classe".</w:t></w:r><w:r><w:rPr><w:rStyle w:val="CommentReference" /></w:rPr><w:annotationRef /></w:r><w:r><w:rPr><w:rStyle w:val="CommentReference" /></w:rPr><w:annotationRef /></w:r></w:p><w:p w:rsidR="4A7A2789" w:rsidP="05D12FCE" w:rsidRDefault="4A7A2789" w14:paraId="02B7CB9D" w14:textId="40BE5418"><w:pPr><w:pStyle w:val="CommentText" /></w:pPr><w:r w:rsidR="05D12FCE"><w:rPr /><w:t>Por essa definição, ambas as partições do exemplo seriam puras.</w:t></w:r></w:p><w:p w:rsidR="4A7A2789" w:rsidP="05D12FCE" w:rsidRDefault="4A7A2789" w14:paraId="6CD09EE0" w14:textId="76CCA158"><w:pPr><w:pStyle w:val="CommentText" /></w:pPr><w:r w:rsidR="05D12FCE"><w:rPr /><w:t>Sugiro rever um dos pontos para deixar consistente: ou o texto deste exemplo ou a definição de partições puras/impuras (talvez fosse mais preciso falar em impureza alta/baixa).</w:t></w:r></w:p></w:comment><w:comment w:initials="MM" w:author="Marcelo Rodrigues de Holanda Maia" w:date="2022-09-09T10:54:28" w:id="1313546104"><w:p w:rsidR="4A7A2789" w:rsidRDefault="4A7A2789" w14:paraId="0B879651" w14:textId="4238B748"><w:pPr><w:pStyle w:val="CommentText" /></w:pPr><w:r w:rsidR="4A7A2789"><w:rPr /><w:t>Esta definição de "partições puras" está inconsistente com o exemplo apresentado em seguida (ver comentário adicional no exemplo)</w:t></w:r><w:r><w:rPr><w:rStyle w:val="CommentReference" /></w:rPr><w:annotationRef /></w:r><w:r><w:rPr><w:rStyle w:val="CommentReference" /></w:rPr><w:annotationRef /></w:r></w:p></w:comment><w:comment w:initials="MM" w:author="Marcelo Rodrigues de Holanda Maia" w:date="2022-09-09T11:56:44" w:id="462953646"><w:p w:rsidR="7AF3765A" w:rsidRDefault="7AF3765A" w14:paraId="6A0C7CFD" w14:textId="0136A6C9"><w:pPr><w:pStyle w:val="CommentText" /></w:pPr><w:r w:rsidR="7AF3765A"><w:rPr /><w:t>Não necessariamente, certo?</w:t></w:r><w:r><w:rPr><w:rStyle w:val="CommentReference" /></w:rPr><w:annotationRef /></w:r></w:p></w:comment><w:comment w:initials="MM" w:author="Marcelo Rodrigues de Holanda Maia" w:date="2022-09-09T14:15:00" w:id="574294490"><w:p w:rsidR="7AF3765A" w:rsidRDefault="7AF3765A" w14:paraId="5AD1A531" w14:textId="32175F11"><w:pPr><w:pStyle w:val="CommentText" /></w:pPr><w:r w:rsidR="7AF3765A"><w:rPr /><w:t>Este título ficou fora de contexto</w:t></w:r><w:r><w:rPr><w:rStyle w:val="CommentReference" /></w:rPr><w:annotationRef /></w:r><w:r><w:rPr><w:rStyle w:val="CommentReference" /></w:rPr><w:annotationRef /></w:r></w:p></w:comment><w:comment w:initials="MM" w:author="Marcelo Rodrigues de Holanda Maia" w:date="2022-09-09T18:54:29" w:id="458632852"><w:p w:rsidR="7C0D74B8" w:rsidRDefault="7C0D74B8" w14:paraId="61D8663E" w14:textId="6386EBCC"><w:pPr><w:pStyle w:val="CommentText" /></w:pPr><w:r w:rsidR="7C0D74B8"><w:rPr /><w:t>Alterei esse exemplo para contemplar a área de Geociências.</w:t></w:r><w:r><w:rPr><w:rStyle w:val="CommentReference" /></w:rPr><w:annotationRef /></w:r><w:r><w:rPr><w:rStyle w:val="CommentReference" /></w:rPr><w:annotationRef /></w:r></w:p></w:comment><w:comment w:initials="EG" w:author="Eduardo Correa Goncalves" w:date="2022-09-12T16:27:02" w:id="786161928"><w:p w:rsidR="73F6F145" w:rsidRDefault="73F6F145" w14:paraId="434C8C90" w14:textId="2CB7B98C"><w:pPr><w:pStyle w:val="CommentText" /></w:pPr><w:r><w:fldChar w:fldCharType="begin" /></w:r><w:r><w:instrText xml:space="preserve"> HYPERLINK "mailto:marcelo.h.maia@ibge.gov.br"</w:instrText></w:r><w:bookmarkStart w:name="_@_434E183ECABE4BC990AEEEA6AB0C99D7Z" w:id="498609156" /><w:r><w:fldChar w:fldCharType="separate" /></w:r><w:bookmarkEnd w:id="498609156" /><w:r w:rsidRPr="73F6F145" w:rsidR="73F6F145"><w:rPr><w:rStyle w:val="Mention" /><w:noProof /></w:rPr><w:t>@Marcelo Rodrigues de Holanda Maia</w:t></w:r><w:r><w:fldChar w:fldCharType="end" /></w:r><w:r w:rsidR="73F6F145"><w:rPr /><w:t xml:space="preserve">  achei excelente a modificação</w:t></w:r><w:r><w:rPr><w:rStyle w:val="CommentReference" /></w:rPr><w:annotationRef /></w:r><w:r><w:rPr><w:rStyle w:val="CommentReference" /></w:rPr><w:annotationRef /></w:r></w:p></w:comment><w:comment w:initials="EG" w:author="Eduardo Correa Goncalves" w:date="2022-09-12T16:33:05" w:id="81094151"><w:p w:rsidR="73F6F145" w:rsidRDefault="73F6F145" w14:paraId="0BC343E3" w14:textId="73FF8D0C"><w:pPr><w:pStyle w:val="CommentText" /></w:pPr><w:r><w:fldChar w:fldCharType="begin" /></w:r><w:r><w:instrText xml:space="preserve"> HYPERLINK "mailto:1807108@ibge.gov.br"</w:instrText></w:r><w:bookmarkStart w:name="_@_4DFB31E1EC57450282B7B121FAA47686Z" w:id="1192353107" /><w:r><w:fldChar w:fldCharType="separate" /></w:r><w:bookmarkEnd w:id="1192353107" /><w:r w:rsidRPr="73F6F145" w:rsidR="73F6F145"><w:rPr><w:rStyle w:val="Mention" /><w:noProof /></w:rPr><w:t>@Aline Bezerra da Silva</w:t></w:r><w:r><w:fldChar w:fldCharType="end" /></w:r><w:r w:rsidR="73F6F145"><w:rPr /><w:t xml:space="preserve"> ok, concordo com o ajuste do Marcelo</w:t></w:r><w:r><w:rPr><w:rStyle w:val="CommentReference" /></w:rPr><w:annotationRef /></w:r><w:r><w:rPr><w:rStyle w:val="CommentReference" /></w:rPr><w:annotationRef /></w:r></w:p></w:comment><w:comment w:initials="EG" w:author="Eduardo Correa Goncalves" w:date="2022-09-12T16:35:59" w:id="1622349616"><w:p w:rsidR="73F6F145" w:rsidRDefault="73F6F145" w14:paraId="2918EAE2" w14:textId="7ED01DDD"><w:pPr><w:pStyle w:val="CommentText" /></w:pPr><w:r><w:fldChar w:fldCharType="begin" /></w:r><w:r><w:instrText xml:space="preserve"> HYPERLINK "mailto:marcelo.h.maia@ibge.gov.br"</w:instrText></w:r><w:bookmarkStart w:name="_@_45E54E8968DE4C10A1BCA938C0329E29Z" w:id="1966296367" /><w:r><w:fldChar w:fldCharType="separate" /></w:r><w:bookmarkEnd w:id="1966296367" /><w:r w:rsidRPr="73F6F145" w:rsidR="73F6F145"><w:rPr><w:rStyle w:val="Mention" /><w:noProof /></w:rPr><w:t>@Marcelo Rodrigues de Holanda Maia</w:t></w:r><w:r><w:fldChar w:fldCharType="end" /></w:r><w:r w:rsidR="73F6F145"><w:rPr /><w:t xml:space="preserve"> verdade... eu acabei omitindo que existe classificação multirrótulo e classificação hierárquica, pois considerei que seriam temas para um curso avançado de CD. Mas esse "em geral" aí ficou legal </w:t></w:r><w:r><w:rPr><w:rStyle w:val="CommentReference" /></w:rPr><w:annotationRef /></w:r><w:r><w:rPr><w:rStyle w:val="CommentReference" /></w:rPr><w:annotationRef /></w:r></w:p></w:comment><w:comment w:initials="EG" w:author="Eduardo Correa Goncalves" w:date="2022-09-12T16:36:22" w:id="938741046"><w:p w:rsidR="73F6F145" w:rsidRDefault="73F6F145" w14:paraId="2800ECD9" w14:textId="3A0554C3"><w:pPr><w:pStyle w:val="CommentText" /></w:pPr><w:r w:rsidR="73F6F145"><w:rPr /><w:t>Ok!</w:t></w:r><w:r><w:rPr><w:rStyle w:val="CommentReference" /></w:rPr><w:annotationRef /></w:r><w:r><w:rPr><w:rStyle w:val="CommentReference" /></w:rPr><w:annotationRef /></w:r></w:p></w:comment><w:comment w:initials="MM" w:author="Marcelo Rodrigues de Holanda Maia" w:date="2022-08-23T18:21:22" w:id="1507243151"><w:p w:rsidR="33014BC5" w:rsidRDefault="33014BC5" w14:paraId="6762AB75" w14:textId="1C25C59B"><w:pPr><w:pStyle w:val="CommentText" /></w:pPr><w:r w:rsidR="33014BC5"><w:rPr /><w:t>Sugiro explicar isso antes do exemplo. Ao ver o exemplo e compará-lo à fórmula o leitor vai sentir falta do denominador. E a explicação só vem depois, neste ponto.</w:t></w:r><w:r><w:rPr><w:rStyle w:val="CommentReference" /></w:rPr><w:annotationRef /></w:r><w:r><w:rPr><w:rStyle w:val="CommentReference" /></w:rPr><w:annotationRef /></w:r></w:p></w:comment><w:comment w:initials="EG" w:author="Eduardo Correa Goncalves" w:date="2022-09-12T17:06:52" w:id="298443484"><w:p w:rsidR="33014BC5" w:rsidRDefault="33014BC5" w14:paraId="0E35CEAC" w14:textId="5620EE24"><w:pPr><w:pStyle w:val="CommentText" /></w:pPr><w:r><w:fldChar w:fldCharType="begin" /></w:r><w:r><w:instrText xml:space="preserve"> HYPERLINK "mailto:marcelo.h.maia@ibge.gov.br"</w:instrText></w:r><w:bookmarkStart w:name="_@_2A0AB465F2CC49E29CA6DC70D8572292Z" w:id="600013260" /><w:r><w:fldChar w:fldCharType="separate" /></w:r><w:bookmarkEnd w:id="600013260" /><w:r w:rsidRPr="33014BC5" w:rsidR="33014BC5"><w:rPr><w:rStyle w:val="Mention" /><w:noProof /></w:rPr><w:t>@Marcelo Rodrigues de Holanda Maia</w:t></w:r><w:r><w:fldChar w:fldCharType="end" /></w:r><w:r w:rsidR="33014BC5"><w:rPr /><w:t xml:space="preserve">  feito</w:t></w:r><w:r><w:rPr><w:rStyle w:val="CommentReference" /></w:rPr><w:annotationRef /></w:r><w:r><w:rPr><w:rStyle w:val="CommentReference" /></w:rPr><w:annotationRef /></w:r></w:p></w:comment><w:comment w:initials="EG" w:author="Eduardo Correa Goncalves" w:date="2022-09-12T17:19:44" w:id="741099839"><w:p w:rsidR="75992630" w:rsidRDefault="75992630" w14:paraId="5349933C" w14:textId="75062289"><w:pPr><w:pStyle w:val="CommentText" /></w:pPr><w:r><w:fldChar w:fldCharType="begin" /></w:r><w:r><w:instrText xml:space="preserve"> HYPERLINK "mailto:marcelo.h.maia@ibge.gov.br"</w:instrText></w:r><w:bookmarkStart w:name="_@_97194DB80FBB4AA3B4F9B18BA5F73E0DZ" w:id="795654303" /><w:r><w:fldChar w:fldCharType="separate" /></w:r><w:bookmarkEnd w:id="795654303" /><w:r w:rsidRPr="75992630" w:rsidR="75992630"><w:rPr><w:rStyle w:val="Mention" /><w:noProof /></w:rPr><w:t>@Marcelo Rodrigues de Holanda Maia</w:t></w:r><w:r><w:fldChar w:fldCharType="end" /></w:r><w:r w:rsidR="75992630"><w:rPr /><w:t xml:space="preserve"> ok, procurei corrigir no texto</w:t></w:r><w:r><w:rPr><w:rStyle w:val="CommentReference" /></w:rPr><w:annotationRef /></w:r><w:r><w:rPr><w:rStyle w:val="CommentReference" /></w:rPr><w:annotationRef /></w:r></w:p></w:comment><w:comment w:initials="EG" w:author="Eduardo Correa Goncalves" w:date="2022-09-12T17:20:12" w:id="1084770528"><w:p w:rsidR="75992630" w:rsidRDefault="75992630" w14:paraId="727B5A29" w14:textId="66C5D965"><w:pPr><w:pStyle w:val="CommentText" /></w:pPr><w:r><w:fldChar w:fldCharType="begin" /></w:r><w:r><w:instrText xml:space="preserve"> HYPERLINK "mailto:marcelo.h.maia@ibge.gov.br"</w:instrText></w:r><w:bookmarkStart w:name="_@_9E9543654C654DFABA787C8DC311A190Z" w:id="866269307" /><w:r><w:fldChar w:fldCharType="separate" /></w:r><w:bookmarkEnd w:id="866269307" /><w:r w:rsidRPr="75992630" w:rsidR="75992630"><w:rPr><w:rStyle w:val="Mention" /><w:noProof /></w:rPr><w:t>@Marcelo Rodrigues de Holanda Maia</w:t></w:r><w:r><w:fldChar w:fldCharType="end" /></w:r><w:r w:rsidR="75992630"><w:rPr /><w:t xml:space="preserve"> ok, tratei no texto lá embaixo</w:t></w:r><w:r><w:rPr><w:rStyle w:val="CommentReference" /></w:rPr><w:annotationRef /></w:r><w:r><w:rPr><w:rStyle w:val="CommentReference" /></w:rPr><w:annotationRef /></w:r></w:p></w:comment><w:comment w:initials="EG" w:author="Eduardo Correa Goncalves" w:date="2022-09-12T17:30:12" w:id="1081911787"><w:p w:rsidR="75992630" w:rsidRDefault="75992630" w14:paraId="2C1245F7" w14:textId="1442985E"><w:pPr><w:pStyle w:val="CommentText" /></w:pPr><w:r><w:fldChar w:fldCharType="begin" /></w:r><w:r><w:instrText xml:space="preserve"> HYPERLINK "mailto:marcelo.h.maia@ibge.gov.br"</w:instrText></w:r><w:bookmarkStart w:name="_@_5F15EFE9532140D691FAC076F09B6951Z" w:id="1272995453" /><w:r><w:fldChar w:fldCharType="separate" /></w:r><w:bookmarkEnd w:id="1272995453" /><w:r w:rsidRPr="75992630" w:rsidR="75992630"><w:rPr><w:rStyle w:val="Mention" /><w:noProof /></w:rPr><w:t>@Marcelo Rodrigues de Holanda Maia</w:t></w:r><w:r><w:fldChar w:fldCharType="end" /></w:r><w:r w:rsidR="75992630"><w:rPr /><w:t xml:space="preserve"> tirei essa informação do livro Han, Pei, Kamber, 2011</w:t></w:r><w:r><w:rPr><w:rStyle w:val="CommentReference" /></w:rPr><w:annotationRef /></w:r></w:p></w:comment><w:comment w:initials="EG" w:author="Eduardo Correa Goncalves" w:date="2022-09-12T17:31:03" w:id="598528006"><w:p w:rsidR="75992630" w:rsidRDefault="75992630" w14:paraId="71CB3C2B" w14:textId="288DA83D"><w:pPr><w:pStyle w:val="CommentText" /></w:pPr><w:r w:rsidR="75992630"><w:rPr /><w:t>Poderia ser outro algoritmo, mas na scikit-learn usam o CART. Acho que nos pacotes do R também. O lance é que o CART não é patenteado, mas o C45 é</w:t></w:r><w:r><w:rPr><w:rStyle w:val="CommentReference" /></w:rPr><w:annotationRef /></w:r></w:p></w:comment><w:comment w:initials="EG" w:author="Eduardo Correa Goncalves" w:date="2022-09-12T17:44:21" w:id="1617301705"><w:p w:rsidR="75992630" w:rsidRDefault="75992630" w14:paraId="34D69779" w14:textId="5A02FA0C"><w:pPr><w:pStyle w:val="CommentText" /></w:pPr><w:r><w:fldChar w:fldCharType="begin" /></w:r><w:r><w:instrText xml:space="preserve"> HYPERLINK "mailto:marcelo.h.maia@ibge.gov.br"</w:instrText></w:r><w:bookmarkStart w:name="_@_DD567C5DC8B746C6A1930802D86312A1Z" w:id="1446263843" /><w:r><w:fldChar w:fldCharType="separate" /></w:r><w:bookmarkEnd w:id="1446263843" /><w:r w:rsidRPr="75992630" w:rsidR="75992630"><w:rPr><w:rStyle w:val="Mention" /><w:noProof /></w:rPr><w:t>@Marcelo Rodrigues de Holanda Maia</w:t></w:r><w:r><w:fldChar w:fldCharType="end" /></w:r><w:r w:rsidR="75992630"><w:rPr /><w:t xml:space="preserve"> troquei</w:t></w:r><w:r><w:rPr><w:rStyle w:val="CommentReference" /></w:rPr><w:annotationRef /></w:r><w:r><w:rPr><w:rStyle w:val="CommentReference" /></w:rPr><w:annotationRef /></w:r></w:p></w:comment><w:comment w:initials="EG" w:author="Eduardo Correa Goncalves" w:date="2022-09-12T17:44:58" w:id="619500203"><w:p w:rsidR="75992630" w:rsidRDefault="75992630" w14:paraId="163987AC" w14:textId="5BDA5555"><w:pPr><w:pStyle w:val="CommentText" /></w:pPr><w:r><w:fldChar w:fldCharType="begin" /></w:r><w:r><w:instrText xml:space="preserve"> HYPERLINK "mailto:breno.oliveira@ibge.gov.br"</w:instrText></w:r><w:bookmarkStart w:name="_@_161BD386297B426E8A000F59AB4F4B9FZ" w:id="1043783229" /><w:r><w:fldChar w:fldCharType="separate" /></w:r><w:bookmarkEnd w:id="1043783229" /><w:r w:rsidRPr="75992630" w:rsidR="75992630"><w:rPr><w:rStyle w:val="Mention" /><w:noProof /></w:rPr><w:t>@Breno Tiago Novello Trotta de Oliveira</w:t></w:r><w:r><w:fldChar w:fldCharType="end" /></w:r><w:r w:rsidR="75992630"><w:rPr /><w:t xml:space="preserve"> acho que aqui você vai ter que encontrar uma base de dados para montar o exemplo.</w:t></w:r><w:r><w:rPr><w:rStyle w:val="CommentReference" /></w:rPr><w:annotationRef /></w:r></w:p></w:comment><w:comment w:initials="BO" w:author="Breno Tiago Novello Trotta de Oliveira" w:date="2022-09-12T20:43:14" w:id="615830016"><w:p w:rsidR="5391290C" w:rsidRDefault="5391290C" w14:paraId="0528E116" w14:textId="3BB2D02B"><w:pPr><w:pStyle w:val="CommentText" /></w:pPr><w:r w:rsidR="5391290C"><w:rPr /><w:t>sim, aqui eu pensei em colocar um link com os comandos para a pagina do Colab que o Marcelo apresentou. Acho que pode ficar assim por enquanto, para não afetar o andamento do storyboard.</w:t></w:r><w:r><w:rPr><w:rStyle w:val="CommentReference" /></w:rPr><w:annotationRef /></w:r></w:p></w:comment><w:comment w:initials="AS" w:author="Aline Bezerra da Silva" w:date="2022-09-16T14:13:17" w:id="883554149"><w:p w:rsidR="16059989" w:rsidRDefault="16059989" w14:paraId="1B07E58F" w14:textId="20F080A6"><w:pPr><w:pStyle w:val="CommentText" /></w:pPr><w:r><w:fldChar w:fldCharType="begin" /></w:r><w:r><w:instrText xml:space="preserve"> HYPERLINK "mailto:thiago.lima@ibge.gov.br"</w:instrText></w:r><w:bookmarkStart w:name="_@_023D4365C06F4F06BDA44FCC7BF7A3EEZ" w:id="1441227354" /><w:r><w:fldChar w:fldCharType="separate" /></w:r><w:bookmarkEnd w:id="1441227354" /><w:r w:rsidRPr="16059989" w:rsidR="16059989"><w:rPr><w:rStyle w:val="Mention" /><w:noProof /></w:rPr><w:t>@Thiago Augusto Silva de Lima</w:t></w:r><w:r><w:fldChar w:fldCharType="end" /></w:r><w:r w:rsidR="16059989"><w:rPr /><w:t xml:space="preserve"> </w:t></w:r><w:r><w:rPr><w:rStyle w:val="CommentReference" /></w:rPr><w:annotationRef /></w:r></w:p></w:comment><w:comment w:initials="AS" w:author="Aline Bezerra da Silva" w:date="2022-09-16T14:21:26" w:id="1443669178"><w:p w:rsidR="16059989" w:rsidRDefault="16059989" w14:paraId="241E545C" w14:textId="5C88574E"><w:pPr><w:pStyle w:val="CommentText" /></w:pPr><w:r><w:fldChar w:fldCharType="begin" /></w:r><w:r><w:instrText xml:space="preserve"> HYPERLINK "mailto:thiago.lima@ibge.gov.br"</w:instrText></w:r><w:bookmarkStart w:name="_@_85946BB911AB404EB658DCF69B7447EBZ" w:id="1561981834" /><w:r><w:fldChar w:fldCharType="separate" /></w:r><w:bookmarkEnd w:id="1561981834" /><w:r w:rsidRPr="16059989" w:rsidR="16059989"><w:rPr><w:rStyle w:val="Mention" /><w:noProof /></w:rPr><w:t>@Thiago Augusto Silva de Lima</w:t></w:r><w:r><w:fldChar w:fldCharType="end" /></w:r><w:r w:rsidR="16059989"><w:rPr /><w:t xml:space="preserve"> </w:t></w:r><w:r><w:rPr><w:rStyle w:val="CommentReference" /></w:rPr><w:annotationRef /></w:r></w:p></w:comment></w:comments>